README.txt
bootstrap.py
buildout.cfg
ldap.cfg
setup.py
patches/getpeereid.patch
src/bda/__init__.py
src/bda.ldap.egg-info/PKG-INFO
src/bda.ldap.egg-info/SOURCES.txt
src/bda.ldap.egg-info/dependency_links.txt
src/bda.ldap.egg-info/entry_points.txt
src/bda.ldap.egg-info/namespace_packages.txt
src/bda.ldap.egg-info/not-zip-safe
src/bda.ldap.egg-info/requires.txt
src/bda.ldap.egg-info/top_level.txt
src/bda/ldap/__init__.py
src/bda/ldap/base.py
src/bda/ldap/base.txt
src/bda/ldap/cache.py
src/bda/ldap/configure.zcml
src/bda/ldap/interfaces.py
src/bda/ldap/node.py
src/bda/ldap/node.txt
src/bda/ldap/properties.py
src/bda/ldap/session.py
src/bda/ldap/session.txt
src/bda/ldap/strcodec.py
src/bda/ldap/tests/__init__.py
src/bda/ldap/tests/prepareslapd.txt
src/bda/ldap/tests/stopslapd.txt
src/bda/ldap/tests/test_ldap.py
testenv/data.ldif