Metadata-Version: 1.0
Name: bda.ldap
Version: 1.5.1
Summary: LDAP convenience library
Home-page: https://svn.plone.org/svn/collective/bda.ldap
Author: Robert Niederreiter
Author-email: dev@bluedynamics.com
License: General Public Licence
Platform: UNKNOWN
Classifier: Development Status :: 4 - Beta
Classifier: Environment :: Web Environment
Classifier: Framework :: Zope2
Classifier: License :: OSI Approved :: GNU General Public License (GPL)
Classifier: Operating System :: OS Independent
Classifier: Programming Language :: Python
Classifier: Topic :: Internet :: WWW/HTTP :: Dynamic Content
